LICENSE
MANIFEST.in
README.rst
setup.py
dblogs/__init__.py
dblogs/admin.py
dblogs/handlers.py
dblogs/models.py
dblogs/tests.py
dblogs/views.py
django_dblogs.egg-info/PKG-INFO
django_dblogs.egg-info/SOURCES.txt
django_dblogs.egg-info/dependency_links.txt
django_dblogs.egg-info/pbr.json
django_dblogs.egg-info/top_level.txt