Metadata-Version: 1.1
Name: django-dblogs
Version: 0.1
Summary: A simple Django app to write logging data to database
Home-page: https://github.com/jian-en/django_dblogs
Author: Fu Jian
Author-email: fujian_en@126.com
License: BSD License
Platform: UNKNOWN
Classifier: Environment :: Web Environment
Classifier: Framework :: Django
Classifier: Intended Audience :: Developers
Classifier: License :: OSI Approved :: BSD License
Classifier: Operating System :: OS Independent
Classifier: Programming Language :: Python
Classifier: Topic :: Internet :: WWW/HTTP
Classifier: Topic :: Internet :: WWW/HTTP :: Dynamic Content
